davia/__init__.py
davia/_version.py
davia/application.py
davia/cli.py
davia/main.py
davia/routers.py
davia/scalar.py
davia/state.py
davia/utils.py
davia-0.1.18.dist-info/METADATA
davia-0.1.18.dist-info/WHEEL
davia-0.1.18.dist-info/entry_points.txt
davia-0.1.18.dist-info/licenses/LICENSE
davia-0.1.18.dist-info/RECORD
