Metadata-Version: 2.4
Name: davia
Version: 0.1.18
Summary: The easiest way to build AI apps from your Python code
Project-URL: Homepage, https://davia.ai
Project-URL: Documentation, https://docs.davia.ai
Project-URL: Repository, https://github.com/davialabs/davia.git
Project-URL: Issues, https://github.com/davialabs/davia/issues
Author-email: Davia <contact@davia.ai>
License-Expression: MIT
License-File: LICENSE
Classifier: Development Status :: 7 - Inactive
Classifier: License :: OSI Approved :: MIT License
Classifier: Operating System :: OS Independent
Classifier: Programming Language :: Python :: 3
Classifier: Programming Language :: Python :: 3.9
Classifier: Programming Language :: Python :: 3.10
Classifier: Programming Language :: Python :: 3.11
Classifier: Programming Language :: Python :: 3.12
Classifier: Topic :: Scientific/Engineering :: Artificial Intelligence
Classifier: Topic :: Software Development :: Build Tools
Classifier: Topic :: Software Development :: User Interfaces
Requires-Python: >=3.9
Requires-Dist: fastapi[standard]>=0.115.12
Requires-Dist: typer>=0.15.3
